ditto/__init__.py
ditto/cli.py
ditto/compat.py
ditto/converter.py
ditto/core.py
ditto/dittolayers.py
ditto/helpers.py
ditto/metric_computer.py
ditto/store.py
ditto/utils.py
ditto/version.py
ditto/consistency/__init__.py
ditto/consistency/check_loads_connected.py
ditto/consistency/check_loops.py
ditto/consistency/check_matched_phases.py
ditto/consistency/check_transformer_phase_path.py
ditto/consistency/check_unique_path.py
ditto/consistency/fix_transformer_phase_path.py
ditto/consistency/fix_undersized_transformers.py
ditto/default_values/__init__.py
ditto/default_values/default_values_json.py
ditto/default_values/opendss_default_values.json
ditto/formats/__init__.py
ditto/formats/gridlabd/__init__.py
ditto/formats/gridlabd/base.py
ditto/formats/gridlabd/gridlabd.py
ditto/formats/gridlabd/schema.json
ditto/metrics/__init__.py
ditto/metrics/network_analysis.py
ditto/models/__init__.py
ditto/models/base.py
ditto/models/capacitor.py
ditto/models/feeder_metadata.py
ditto/models/generator.py
ditto/models/line.py
ditto/models/load.py
ditto/models/load_layer.py
ditto/models/meter.py
ditto/models/node.py
ditto/models/phase_capacitor.py
ditto/models/phase_load.py
ditto/models/phase_reactor.py
ditto/models/phase_storage.py
ditto/models/phase_winding.py
ditto/models/photovoltaic.py
ditto/models/position.py
ditto/models/power_source.py
ditto/models/powertransformer.py
ditto/models/reactor.py
ditto/models/regulator.py
ditto/models/storage.py
ditto/models/timeseries.py
ditto/models/weather_layer.py
ditto/models/winding.py
ditto/models/wire.py
ditto/modify/__init__.py
ditto/modify/modify.py
ditto/modify/system_structure.py
ditto/network/__init__.py
ditto/network/network.py
ditto/readers/__init__.py
ditto/readers/abstract_reader.py
ditto/readers/csv/__init__.py
ditto/readers/csv/adjust_load.py
ditto/readers/csv/read.py
ditto/readers/csv/test.py
ditto/readers/cyme/__init__.py
ditto/readers/cyme/read.py
ditto/readers/demo/__init__.py
ditto/readers/demo/read.py
ditto.py-0.2.4.dist-info/LICENSE
ditto.py-0.2.4.dist-info/METADATA
ditto.py-0.2.4.dist-info/WHEEL
ditto.py-0.2.4.dist-info/entry_points.txt
ditto.py-0.2.4.dist-info/top_level.txt
ditto.py-0.2.4.dist-info/RECORD
