Metadata-Version: 2.1
Name: ditto.py
Version: 0.2.4
Summary: Distribution Feeder Conversion Tool
Home-page: https://github.com/NREL/ditto
Author: Tarek Elgindy
Author-email: tarek.elgindy@nrel.gov
License: BSD license
Keywords: ditto
Platform: UNKNOWN
Classifier: Development Status :: 2 - Pre-Alpha
Classifier: Intended Audience :: Developers
Classifier: License :: OSI Approved :: BSD License
Classifier: Natural Language :: English
Classifier: Programming Language :: Python :: 3.8
Classifier: Programming Language :: Python :: 3.9
Classifier: Programming Language :: Python :: 3.10
Classifier: Programming Language :: Python :: 3.11
Classifier: Programming Language :: Python :: 3.12
Requires-Dist: click ~=8.0
Requires-Dist: future ~=0.18
Requires-Dist: networkx ~=2.5
Requires-Dist: six ~=1.16
Requires-Dist: traitlets ~=5.1
Requires-Dist: json-tricks ~=3.16
Requires-Dist: pandas ~=2.0
Requires-Dist: numpy ~=1.20
Provides-Extra: all
Requires-Dist: lxml ~=4.9 ; extra == 'all'
Requires-Dist: pandas ~=2.0 ; extra == 'all'
Requires-Dist: scipy ~=1.7 ; extra == 'all'
Requires-Dist: numpy ~=1.20 ; extra == 'all'
Requires-Dist: XlsxWriter ~=3.0 ; extra == 'all'
Requires-Dist: OpenDSSDirect.py ~=0.7 ; extra == 'all'
Requires-Dist: pandas ; extra == 'all'
Requires-Dist: xlrd ~=2.0 ; extra == 'all'
Requires-Dist: croniter ~=1.3 ; extra == 'all'
Requires-Dist: pandas-access ~=0.0 ; extra == 'all'
Requires-Dist: bokeh ; extra == 'all'
Requires-Dist: xmltodict ; extra == 'all'
Provides-Extra: cyme
Requires-Dist: numpy ~=1.20 ; extra == 'cyme'
Provides-Extra: dev
Requires-Dist: backports.tempfile ~=1.0 ; extra == 'dev'
Requires-Dist: pytest ~=7.4 ; extra == 'dev'
Requires-Dist: pytest-cov ~=4.0 ; extra == 'dev'
Requires-Dist: sphinx-rtd-theme ~=1.1 ; extra == 'dev'
Requires-Dist: nbsphinx ~=0.8 ; extra == 'dev'
Requires-Dist: sphinxcontrib-napoleon ~=0.7 ; extra == 'dev'
Requires-Dist: ghp-import ~=2.1 ; extra == 'dev'
Requires-Dist: pypandoc ; extra == 'dev'
Requires-Dist: black ; extra == 'dev'
Requires-Dist: pre-commit ; extra == 'dev'
Provides-Extra: dew
Requires-Dist: numpy ~=1.20 ; extra == 'dew'
Requires-Dist: xlrd ~=2.0 ; extra == 'dew'
Provides-Extra: ephasor
Requires-Dist: numpy ~=1.20 ; extra == 'ephasor'
Requires-Dist: pandas ; extra == 'ephasor'
Provides-Extra: extras
Requires-Dist: lxml ~=4.9 ; extra == 'extras'
Requires-Dist: pandas ~=2.0 ; extra == 'extras'
Requires-Dist: scipy ~=1.7 ; extra == 'extras'
Requires-Dist: numpy ~=1.20 ; extra == 'extras'
Requires-Dist: XlsxWriter ~=3.0 ; extra == 'extras'
Provides-Extra: gridlabd
Requires-Dist: croniter ~=1.3 ; extra == 'gridlabd'
Requires-Dist: numpy ~=1.20 ; extra == 'gridlabd'
Provides-Extra: opendss
Requires-Dist: OpenDSSDirect.py ~=0.7 ; extra == 'opendss'
Requires-Dist: pandas ; extra == 'opendss'
Requires-Dist: numpy ~=1.20 ; extra == 'opendss'
Provides-Extra: synergi
Requires-Dist: numpy ~=1.20 ; extra == 'synergi'
Requires-Dist: pandas-access ~=0.0 ; extra == 'synergi'
Provides-Extra: test
Requires-Dist: backports.tempfile ~=1.0 ; extra == 'test'
Requires-Dist: pytest ~=7.4 ; extra == 'test'
Requires-Dist: pytest-cov ~=4.0 ; extra == 'test'
Requires-Dist: sphinx-rtd-theme ~=1.1 ; extra == 'test'
Requires-Dist: nbsphinx ~=0.8 ; extra == 'test'
Requires-Dist: sphinxcontrib-napoleon ~=0.7 ; extra == 'test'
Requires-Dist: ghp-import ~=2.1 ; extra == 'test'
Provides-Extra: windmil
Requires-Dist: bokeh ; extra == 'windmil'
Requires-Dist: xmltodict ; extra == 'windmil'
